Metadata-Version: 2.1
Name: django-vuejs-translate
Version: 0.6.2
Summary: Generating translations from strings inside vuejs
Home-page: https://gitlab.com/cyberbudy/django-vuejs-translate
Author: cyberbudy
Author-email: cyberbudy@gmail.com
License: MIT
Platform: UNKNOWN
Classifier: Environment :: Web Environment
Classifier: Framework :: Django
Classifier: Intended Audience :: Developers
Classifier: Programming Language :: Python :: 3
